Workbook

Sheet Monthly P&L
A1: ALLONE MONTHLY P&L | B1: M1 | C1: M2 | D1: M3 | E1: M4 | F1: M5 | G1: M6 | H1: M7 | I1: M8 | J1: M9 | K1: M10 | L1: M11 | M1: M12 | N1: Y1 TOTAL | O1: M13 | P1: M14 | Q1: M15 | R1: M16 | S1: M17 | T1: M18 | U1: M19 | V1: M20 | W1: M21 | X1: M22 | Y1: M23 | Z1: M24 | AA1: Y2 TOTAL | AB1: 2-YR TOTAL
A2: HEADCOUNT
A3: Sales Team | B3: 4 | C3: 4 | D3: 5 | E3: 5 | F3: 6 | G3: 6 | H3: 7 | I3: 8 | J3: 8 | K3: 9 | L3: 9 | M3: 10 | N3: 10 | O3: 10 | P3: 11 | Q3: 11 | R3: 12 | S3: 12 | T3: 13 | U3: 13 | V3: 14 | W3: 14 | X3: 15 | Y3: 15 | Z3: 15 | AB3: =Z3 -> 15
A4: Tech Team | B4: 2 | C4: 2 | D4: 2 | E4: 3 | F4: 3 | G4: 4 | H4: 4 | I4: 4 | J4: 5 | K4: 5 | L4: 6 | M4: 6 | N4: 6 | O4: 6 | P4: 6 | Q4: 6 | R4: 7 | S4: 7 | T4: 7 | U4: 7 | V4: 8 | W4: 8 | X4: 8 | Y4: 8 | Z4: 8 | AB4: =Z4 -> 8
A6: PROJECTS
A7: New Projects | B7: 1 | C7: 1 | D7: 2 | E7: 2 | F7: 3 | G7: 4 | H7: 5 | I7: 5 | J7: 6 | K7: 7 | L7: 7 | M7: 8 | N7: =SUM(B7:M7) -> 51 | O7: 8 | P7: 9 | Q7: 10 | R7: 11 | S7: 12 | T7: 13 | U7: 14 | V7: 15 | W7: 16 | X7: 17 | Y7: 18 | Z7: 20 | AA7: =SUM(O7:Z7) -> 163 | AB7: =N7+AA7 -> 214
A8: Cumulative Projects | B8: =B7 -> 1 | C8: =B8+C7 -> 2 | D8: =C8+D7 -> 4 | E8: =D8+E7 -> 6 | F8: =E8+F7 -> 9 | G8: =F8+G7 -> 13 | H8: =G8+H7 -> 18 | I8: =H8+I7 -> 23 | J8: =I8+J7 -> 29 | ... M8: =L8+M7 -> 51 | N8: =M8 -> 51 | O8: =M8+O7 -> 59 | P8: =O8+P7 -> 68 | Q8: =P8+Q7 -> 78 | R8: =Q8+R7 -> 89 | S8: =R8+S7 -> 101 | T8: =S8+T7 -> 114 | U8: =T8+U7 -> 128 | V8: =U8+V7 -> 143 | W8: =V8+W7 -> 159 | ... Z8: =Y8+Z7 -> 214 | AB8: =Z8 -> 214
A12: REVENUE
A13: Total Revenue | B13: =B7*2500 -> 2500 | C13: =C7*2500 -> 2500 | D13: =D7*2500 -> 5000 | E13: =E7*2500 -> 5000 | F13: =F7*2500 -> 7500 | G13: =G7*3500 -> 14000 | H13: =H7*3500 -> 17500 | I13: =I7*3500 -> 17500 | J13: =J7*3500 -> 21000 | K13: =K7*3500 -> 24500 | L13: =L7*3500 -> 24500 | M13: =M7*3500 -> 28000 | N13: =SUM(B13:M13) -> 169500 | O13: =O7*4500 -> 36000 | P13: =P7*4500 -> 40500 | Q13: =Q7*4500 -> 45000 | R13: =R7*4500 -> 49500 | S13: =S7*4500 -> 54000 | T13: =T7*4500 -> 58500 | U13: =U7*4500 -> 63000 | V13: =V7*4500 -> 67500 | ... Z13: =Z7*4500 -> 90000 | AA13: =SUM(O13:Z13) -> 733500 | AB13: =N13+AA13 -> 903000
A15: COST OF REVENUE
A16: Infrastructure | B16: =600+B13*'Key Assumptions'!$B$25 -> 725 | C16: =600+C13*'Key Assumptions'!$B$25 -> 725 | D16: =600+D13*'Key Assumptions'!$B$25 -> 850 | E16: =600+E13*'Key Assumptions'!$B$25 -> 850 | F16: =600+F13*'Key Assumptions'!$B$25 -> 975 | G16: =600+G13*'Key Assumptions'!$B$25 -> 1300 | H16: =800+H13*'Key Assumptions'!$B$26 -> 887.5 | I16: =800+I13*'Key Assumptions'!$B$26 -> 887.5 | J16: =800+J13*'Key Assumptions'!$B$26 -> 905 | K16: =800+K13*'Key Assumptions'!$B$26 -> 922.5 | L16: =800+L13*'Key Assumptions'!$B$26 -> 922.5 | M16: =800+M13*'Key Assumptions'!$B$26 -> 940 | N16: =SUM(B16:M16) -> 10890 | O16: =800+O13*'Key Assumptions'!$B$26 -> 980 | P16: =800+P13*'Key Assumptions'!$B$26 -> 1002.5 | Q16: =800+Q13*'Key Assumptions'!$B$26 -> 1025 | R16: =800+R13*'Key Assumptions'!$B$26 -> 1047.5 | S16: =800+S13*'Key Assumptions'!$B$26 -> 1070 | T16: =800+T13*'Key Assumptions'!$B$26 -> 1092.5 | U16: =800+U13*'Key Assumptions'!$B$26 -> 1115 | V16: =800+V13*'Key Assumptions'!$B$26 -> 1137.5 | ... Z16: =800+Z13*'Key Assumptions'!$B$26 -> 1250 | AA16: =SUM(O16:Z16) -> 13267.5 | AB16: =N16+AA16 -> 24157.5
A17: Sales Commission | B17: =B13*'Key Assumptions'!$B$8 -> 250 | C17: =C13*'Key Assumptions'!$B$8 -> 250 | D17: =D13*'Key Assumptions'!$B$8 -> 500 | E17: =E13*'Key Assumptions'!$B$8 -> 500 | F17: =F13*'Key Assumptions'!$B$8 -> 750 | G17: =G13*'Key Assumptions'!$B$8 -> 1400 | H17: =H13*'Key Assumptions'!$B$8 -> 1750 | I17: =I13*'Key Assumptions'!$B$8 -> 1750 | ... M17: =M13*'Key Assumptions'!$B$8 -> 2800 | N17: =SUM(B17:M17) -> 16950 | O17: =O13*'Key Assumptions'!$B$8 -> 3600 | P17: =P13*'Key Assumptions'!$B$8 -> 4050 | Q17: =Q13*'Key Assumptions'!$B$8 -> 4500 | R17: =R13*'Key Assumptions'!$B$8 -> 4950 | S17: =S13*'Key Assumptions'!$B$8 -> 5400 | T17: =T13*'Key Assumptions'!$B$8 -> 5850 | U17: =U13*'Key Assumptions'!$B$8 -> 6300 | V17: =V13*'Key Assumptions'!$B$8 -> 6750 | ... Z17: =Z13*'Key Assumptions'!$B$8 -> 9000 | AA17: =SUM(O17:Z17) -> 73350 | AB17: =N17+AA17 -> 90300
A18: Total COGS | B18: =B16+B17 -> 975 | C18: =C16+C17 -> 975 | D18: =D16+D17 -> 1350 | E18: =E16+E17 -> 1350 | F18: =F16+F17 -> 1725 | G18: =G16+G17 -> 2700 | H18: =H16+H17 -> 2637.5 | I18: =I16+I17 -> 2637.5 | ... M18: =M16+M17 -> 3740 | N18: =SUM(B18:M18) -> 27840 | O18: =O16+O17 -> 4580 | P18: =P16+P17 -> 5052.5 | Q18: =Q16+Q17 -> 5525 | R18: =R16+R17 -> 5997.5 | S18: =S16+S17 -> 6470 | T18: =T16+T17 -> 6942.5 | U18: =U16+U17 -> 7415 | V18: =V16+V17 -> 7887.5 | ... Z18: =Z16+Z17 -> 10250 | AA18: =SUM(O18:Z18) -> 86617.5 | AB18: =N18+AA18 -> 114457.5
A20: GROSS PROFIT | B20: =B13-B18 -> 1525 | C20: =C13-C18 -> 1525 | D20: =D13-D18 -> 3650 | E20: =E13-E18 -> 3650 | F20: =F13-F18 -> 5775 | G20: =G13-G18 -> 11300 | H20: =H13-H18 -> 14862.5 | I20: =I13-I18 -> 14862.5 | ... M20: =M13-M18 -> 24260 | N20: =SUM(B20:M20) -> 141660 | O20: =O13-O18 -> 31420 | P20: =P13-P18 -> 35447.5 | Q20: =Q13-Q18 -> 39475 | R20: =R13-R18 -> 43502.5 | S20: =S13-S18 -> 47530 | T20: =T13-T18 -> 51557.5 | U20: =U13-U18 -> 55585 | V20: =V13-V18 -> 59612.5 | ... Z20: =Z13-Z18 -> 79750 | AA20: =SUM(O20:Z20) -> 646882.5 | AB20: =N20+AA20 -> 788542.5
A21: Gross Margin % | B21: =IF(B13=0,0,B20/B13) -> 0.61 | C21: =IF(C13=0,0,C20/C13) -> 0.61 | D21: =IF(D13=0,0,D20/D13) -> 0.73 | E21: =IF(E13=0,0,E20/E13) -> 0.73 | F21: =IF(F13=0,0,F20/F13) -> 0.77 | G21: =IF(G13=0,0,G20/G13) -> 0.80714286 | H21: =IF(H13=0,0,H20/H13) -> 0.84928571 | I21: =IF(I13=0,0,I20/I13) -> 0.84928571 | ... M21: =IF(M13=0,0,M20/M13) -> 0.86642857 | N21: =N20/N13 -> 0.83575221 | O21: =IF(O13>0,O20/O13,0) -> 0.87277778 | P21: =IF(P13>0,P20/P13,0) -> 0.87524691 | Q21: =IF(Q13>0,Q20/Q13,0) -> 0.87722222 | R21: =IF(R13>0,R20/R13,0) -> 0.87883838 | S21: =IF(S13>0,S20/S13,0) -> 0.88018519 | T21: =IF(T13>0,T20/T13,0) -> 0.88132479 | U21: =IF(U13>0,U20/U13,0) -> 0.88230159 | V21: =IF(V13>0,V20/V13,0) -> 0.88314815 | ... Z21: =IF(Z13>0,Z20/Z13,0) -> 0.88611111 | AA21: =AA20/AA13 -> 0.88191207 | AB21: =AB20/AB13 -> 0.87324751
A23: OPERATING EXPENSES
A24: Tech Team Salaries | B24: =B4*'Key Assumptions'!$B$16 -> 1000 | C24: =C4*'Key Assumptions'!$B$16 -> 1000 | D24: =D4*'Key Assumptions'!$B$16 -> 1000 | E24: =E4*'Key Assumptions'!$B$16 -> 1500 | F24: =F4*'Key Assumptions'!$B$16 -> 1500 | G24: =G4*'Key Assumptions'!$B$16 -> 2000 | H24: =H4*'Key Assumptions'!$B$17 -> 2600 | I24: =I4*'Key Assumptions'!$B$17 -> 2600 | J24: =J4*'Key Assumptions'!$B$17 -> 3250 | K24: =K4*'Key Assumptions'!$B$17 -> 3250 | L24: =L4*'Key Assumptions'!$B$17 -> 3900 | M24: =M4*'Key Assumptions'!$B$17 -> 3900 | N24: =SUM(B24:M24) -> 27500 | O24: =O4*'Key Assumptions'!$B$18 -> 5100 | P24: =P4*'Key Assumptions'!$B$18 -> 5100 | Q24: =Q4*'Key Assumptions'!$B$18 -> 5100 | R24: =R4*'Key Assumptions'!$B$18 -> 5950 | S24: =S4*'Key Assumptions'!$B$18 -> 5950 | T24: =T4*'Key Assumptions'!$B$18 -> 5950 | U24: =U4*'Key Assumptions'!$B$18 -> 5950 | V24: =V4*'Key Assumptions'!$B$18 -> 6800 | ... Z24: =Z4*'Key Assumptions'!$B$18 -> 6800 | AA24: =SUM(O24:Z24) -> 73100 | AB24: =N24+AA24 -> 100600
A25: Founder Salaries | B25: ='Key Assumptions'!$B$21 -> 3000 | C25: ='Key Assumptions'!$B$21 -> 3000 | D25: ='Key Assumptions'!$B$21 -> 3000 | E25: ='Key Assumptions'!$B$21 -> 3000 | F25: ='Key Assumptions'!$B$21 -> 3000 | G25: ='Key Assumptions'!$B$21 -> 3000 | H25: ='Key Assumptions'!$B$21 -> 3000 | I25: ='Key Assumptions'!$B$21 -> 3000 | ... M25: ='Key Assumptions'!$B$21 -> 3000 | N25: =SUM(B25:M25) -> 36000 | O25: ='Key Assumptions'!$B$21 -> 3000 | P25: ='Key Assumptions'!$B$21 -> 3000 | Q25: ='Key Assumptions'!$B$21 -> 3000 | R25: ='Key Assumptions'!$B$21 -> 3000 | S25: ='Key Assumptions'!$B$21 -> 3000 | T25: ='Key Assumptions'!$B$21 -> 3000 | U25: ='Key Assumptions'!$B$21 -> 3000 | V25: ='Key Assumptions'!$B$21 -> 3000 | ... Z25: ='Key Assumptions'!$B$21 -> 3000 | AA25: =SUM(O25:Z25) -> 36000 | AB25: =N25+AA25 -> 72000
A26: Marketing | B26: 1500 | C26: 1500 | D26: 1500 | E26: 1500 | F26: 1500 | G26: 1500 | H26: 3000 | I26: 3000 | J26: 3000 | K26: 3000 | L26: 3000 | M26: 3000 | N26: =SUM(B26:M26) -> 27000 | O26: 4000 | P26: 4000 | Q26: 4000 | R26: 4000 | S26: 4000 | T26: 4000 | U26: 4000 | V26: 4000 | W26: 4000 | X26: 4000 | Y26: 4000 | Z26: 4000 | AA26: =SUM(O26:Z26) -> 48000 | AB26: =N26+AA26 -> 75000
A27: Depreciation | B27: 67 | C27: 67 | D27: 67 | E27: 67 | F27: 67 | G27: 67 | H27: 1733 | I27: 1733 | J27: 1733 | K27: 1733 | L27: 1733 | M27: 1733 | N27: =SUM(B27:M27) -> 10800 | O27: 1733 | P27: 1733 | Q27: 1733 | R27: 1733 | S27: 1733 | T27: 1733 | U27: 1733 | V27: 1733 | W27: 1733 | X27: 1733 | Y27: 1733 | Z27: 1733 | AA27: =SUM(O27:Z27) -> 20796 | AB27: =N27+AA27 -> 31596
A28: Total OpEx | B28: =B24+B25+B26+B27 -> 5567 | C28: =C24+C25+C26+C27 -> 5567 | D28: =D24+D25+D26+D27 -> 5567 | E28: =E24+E25+E26+E27 -> 6067 | F28: =F24+F25+F26+F27 -> 6067 | G28: =G24+G25+G26+G27 -> 6567 | H28: =H24+H25+H26+H27 -> 10333 | I28: =I24+I25+I26+I27 -> 10333 | ... M28: =M24+M25+M26+M27 -> 11633 | N28: =SUM(B28:M28) -> 101300 | O28: =O24+O25+O26+O27 -> 13833 | P28: =P24+P25+P26+P27 -> 13833 | Q28: =Q24+Q25+Q26+Q27 -> 13833 | R28: =R24+R25+R26+R27 -> 14683 | S28: =S24+S25+S26+S27 -> 14683 | T28: =T24+T25+T26+T27 -> 14683 | U28: =U24+U25+U26+U27 -> 14683 | V28: =V24+V25+V26+V27 -> 15533 | ... Z28: =Z24+Z25+Z26+Z27 -> 15533 | AA28: =SUM(O28:Z28) -> 177896 | AB28: =N28+AA28 -> 279196
A30: EBITDA | B30: =B20-B28 -> -4042 | C30: =C20-C28 -> -4042 | D30: =D20-D28 -> -1917 | E30: =E20-E28 -> -2417 | F30: =F20-F28 -> -292 | G30: =G20-G28 -> 4733 | H30: =H20-H28 -> 4529.5 | I30: =I20-I28 -> 4529.5 | ... M30: =M20-M28 -> 12627 | N30: =SUM(B30:M30) -> 40360 | O30: =O20-O28 -> 17587 | P30: =P20-P28 -> 21614.5 | Q30: =Q20-Q28 -> 25642 | R30: =R20-R28 -> 28819.5 | S30: =S20-S28 -> 32847 | T30: =T20-T28 -> 36874.5 | U30: =U20-U28 -> 40902 | V30: =V20-V28 -> 44079.5 | ... Z30: =Z20-Z28 -> 64217 | AA30: =SUM(O30:Z30) -> 468986.5 | AB30: =N30+AA30 -> 509346.5
A31: EBITDA Margin % | B31: =IF(B13=0,0,B30/B13) -> -1.6168 | C31: =IF(C13=0,0,C30/C13) -> -1.6168 | D31: =IF(D13=0,0,D30/D13) -> -0.3834 | E31: =IF(E13=0,0,E30/E13) -> -0.4834 | F31: =IF(F13=0,0,F30/F13) -> -0.038933333 | G31: =IF(G13=0,0,G30/G13) -> 0.33807143 | H31: =IF(H13=0,0,H30/H13) -> 0.25882857 | I31: =IF(I13=0,0,I30/I13) -> 0.25882857 | ... M31: =IF(M13=0,0,M30/M13) -> 0.45096429 | N31: =N30/N13 -> 0.23811209 | O31: =IF(O13>0,O30/O13,0) -> 0.48852778 | P31: =IF(P13>0,P30/P13,0) -> 0.53369136 | Q31: =IF(Q13>0,Q30/Q13,0) -> 0.56982222 | R31: =IF(R13>0,R30/R13,0) -> 0.58221212 | S31: =IF(S13>0,S30/S13,0) -> 0.60827778 | T31: =IF(T13>0,T30/T13,0) -> 0.63033333 | U31: =IF(U13>0,U30/U13,0) -> 0.6492381 | V31: =IF(V13>0,V30/V13,0) -> 0.65302963 | ... Z31: =IF(Z13>0,Z30/Z13,0) -> 0.71352222 | AA31: =AA30/AA13 -> 0.63938173 | AB31: =AB30/AB13 -> 0.56406035
A39: NET INCOME | B39: =B30-B37 -> -4042 | C39: =C30-C37 -> -4042 | D39: =D30-D37 -> -1917 | E39: =E30-E37 -> -2417 | F39: =F30-F37 -> -292 | G39: =G30-G37 -> 4733 | H39: =H30-H37 -> 4529.5 | I39: =I30-I37 -> 4529.5 | ... M39: =M30-M37 -> 12627 | N39: =SUM(B39:M39) -> 40360 | O39: =O20-O28 -> 17587 | P39: =P20-P28 -> 21614.5 | Q39: =Q20-Q28 -> 25642 | R39: =R20-R28 -> 28819.5 | S39: =S20-S28 -> 32847 | T39: =T20-T28 -> 36874.5 | U39: =U20-U28 -> 40902 | V39: =V20-V28 -> 44079.5 | ... Z39: =Z20-Z28 -> 64217 | AA39: =SUM(O39:Z39) -> 468986.5 | AB39: =N39+AA39 -> 509346.5
A40: Net Margin % | B40: =IF(B13=0,0,B39/B13) -> -1.6168 | C40: =IF(C13=0,0,C39/C13) -> -1.6168 | D40: =IF(D13=0,0,D39/D13) -> -0.3834 | E40: =IF(E13=0,0,E39/E13) -> -0.4834 | F40: =IF(F13=0,0,F39/F13) -> -0.038933333 | G40: =IF(G13=0,0,G39/G13) -> 0.33807143 | H40: =IF(H13=0,0,H39/H13) -> 0.25882857 | I40: =IF(I13=0,0,I39/I13) -> 0.25882857 | ... M40: =IF(M13=0,0,M39/M13) -> 0.45096429 | N40: =N39/N13 -> 0.23811209 | O40: =IF(O13>0,O39/O13,0) -> 0.48852778 | P40: =IF(P13>0,P39/P13,0) -> 0.53369136 | Q40: =IF(Q13>0,Q39/Q13,0) -> 0.56982222 | R40: =IF(R13>0,R39/R13,0) -> 0.58221212 | S40: =IF(S13>0,S39/S13,0) -> 0.60827778 | T40: =IF(T13>0,T39/T13,0) -> 0.63033333 | U40: =IF(U13>0,U39/U13,0) -> 0.6492381 | V40: =IF(V13>0,V39/V13,0) -> 0.65302963 | ... Z40: =IF(Z13>0,Z39/Z13,0) -> 0.71352222 | AA40: =AA39/AA13 -> 0.63938173 | AB40: =AB39/AB13 -> 0.56406035
A42: INVESTMENT PAYBACK
A43: Cumulative Net Income | B43: =B39 -> -4042 | C43: =B43+C39 -> -8084 | D43: =C43+D39 -> -10001 | E43: =D43+E39 -> -12418 | F43: =E43+F39 -> -12710 | G43: =F43+G39 -> -7977 | H43: =G43+H39 -> -3447.5 | I43: =H43+I39 -> 1082 | J43: =I43+J39 -> 8094 | ... M43: =L43+M39 -> 40360 | N43: =M43 -> 40360 | O43: =M43+O39 -> 57947 | P43: =O43+P39 -> 79561.5 | Q43: =P43+Q39 -> 105203.5 | R43: =Q43+R39 -> 134023 | S43: =R43+S39 -> 166870 | T43: =S43+T39 -> 203744.5 | U43: =T43+U39 -> 244646.5 | V43: =U43+V39 -> 288726 | W43: =V43+W39 -> 336833 | ... Z43: =Y43+Z39 -> 509346.5 | AA43: =Z43 -> 509346.5 | AB43: =Z43 -> 509346.5
A44: Investment Remaining | B44: =MAX(0,240000-B43) -> 244042 | C44: =MAX(0,240000-C43) -> 248084 | D44: =MAX(0,240000-D43) -> 250001 | E44: =MAX(0,240000-E43) -> 252418 | F44: =MAX(0,240000-F43) -> 252710 | G44: =MAX(0,240000-G43) -> 247977 | H44: =MAX(0,240000-H43) -> 243447.5 | I44: =MAX(0,240000-I43) -> 238918 | ... AB44: =MAX(0,240000-AB43) -> 0
A45: Payback Achieved? | B45: =IF(B44<=0,"✓ YES","NO") -> NO | C45: =IF(C44<=0,"✓ YES","NO") -> NO | D45: =IF(D44<=0,"✓ YES","NO") -> NO | E45: =IF(E44<=0,"✓ YES","NO") -> NO | F45: =IF(F44<=0,"✓ YES","NO") -> NO | G45: =IF(G44<=0,"✓ YES","NO") -> NO | H45: =IF(H44<=0,"✓ YES","NO") -> NO | I45: =IF(I44<=0,"✓ YES","NO") -> NO | ... AB45: =IF(AB44<=0,"✓ YES","NO") -> ✓ YES

Sheet Key Assumptions
A1: KEY ASSUMPTIONS
A2: Assumption | B2: Value | C2: Notes
A4: PRICING
A5: Price per project (M1-M5) | B5: 2500 | C5: Early clients
A6: Price per project (M6-M12) | B6: 3500 | C6: Growing reputation
A7: Price per project (M13-M24) | B7: 4500 | C7: Enterprise clients
A8: Sales commission | B8: 0.1 | C8: 10% to affiliates
A10: TECH SALARIES
A11: New hire (0-6 months) | B11: 500 | C11: Starting salary
A12: Mid-level (6-12 months) | B12: 800 | C12: After 6 months
A13: Senior (12+ months) | B13: 1200 | C13: After 12 months
A15: BLENDED RATES (for model)
A16: M1-M6 blended rate | B16: 500 | C16: All new hires
A17: M7-M12 blended rate | B17: 650 | C17: ~50% senior, ~50% new
A18: M13-M24 blended rate | B18: 850 | C18: Mix of tenure levels
A20: OTHER COSTS
A21: Founder salary | B21: 3000 | C21: Monthly
A22: Marketing (M1-M6) | B22: 1500 | C22: Monthly
A23: Marketing (M7-M12) | B23: 3000 | C23: Monthly, scaled
A24: Marketing (M13+) | B24: 4000 | C24: Monthly, mature
A25: Infrastructure (M1-M6) | B25: 0.05 | C25: 5% of revenue (cloud APIs)
A26: Infrastructure (M7+) | B26: 0.005 | C26: 0.5% of revenue (own GPUs)
A27: INVESTMENT
A28: Stage 1 (Pre-seed) | B28: 40000 | C28: 10% equity, M1
A29: Stage 2 (Seed) | B29: 200000 | C29: 15% equity, M7
A30: Total investment | B30: =B28+B29 -> 240000 | C30: 25% total equity
A32: TEAM
A33: Starting tech team (M1) | B33: 2 | C33: Developers
A34: Tech team M12 | B34: 6 | C34: End of Year 1
A35: Tech team M24 | B35: 8 | C35: End of Year 2
A36: Sales team | B36: Commission-only | C36: No fixed salary cost
A38: DEPRECIATION
A39: Depreciation period (months) | B39: 60 | C39: 5 years
A40: Initial equipment (M1) | B40: 4000 | C40: Computers, setup
A41: Stage 2 equipment (M7) | B41: 100000 | C41: GPU infrastructure

Sheet Unit Economics
A1: UNIT ECONOMICS BY PRICING TIER
B2: Tier 1 | C2: Tier 2 | D2: Tier 3
A3: REVENUE PER PROJECT | B3: M1-M5 | C3: M6-M12 | D3: M13-M24
A4: Price per project | B4: 2500 | C4: 3500 | D4: 4500
A5: Sales commission (10%) | B5: =-B4*0.1 -> -250 | C5: =-C4*0.1 -> -350 | D5: =-D4*0.1 -> -450
A6: Net revenue to ALLONE | B6: =B4+B5 -> 2250 | C6: =C4+C5 -> 3150 | D6: =D4+D5 -> 4050
A8: COSTS PER PROJECT
A9: Infrastructure cost | B9: =B4*0.05 -> 125 | C9: =C4*0.05 -> 175 | D9: =D4*0.005 -> 22.5
A10: Delivery labor | B10: 200 | C10: 250 | D10: 300
A11: Total variable cost | B11: =B9+B10 -> 325 | C11: =C9+C10 -> 425 | D11: =D9+D10 -> 322.5
A13: MARGINS
A14: Gross profit per project | B14: =B6-B11 -> 1925 | C14: =C6-C11 -> 2725 | D14: =D6-D11 -> 3727.5
A15: Gross margin % | B15: =B14/B4 -> 0.77 | C15: =C14/C4 -> 0.77857143 | D15: =D14/D4 -> 0.82833333
A17: BREAK-EVEN
A18: Monthly fixed costs (M1-M6) | B18: ='Key Assumptions'!B11+'Key Assumptions'!B12 -> 1300
A19: Monthly fixed costs (M7+) | C19: ='Key Assumptions'!B11+'Key Assumptions'!B13 -> 1700 | D19: ='Key Assumptions'!B11+'Key Assumptions'!B13 -> 1700
A20: Break-even projects/month | B20: =CEILING(B18/B14,1) -> 1 | C20: =CEILING(C19/C14,1) -> 1 | D20: =CEILING(D19/D14,1) -> 1
A21: MODEL TYPE: One-time $2,500 project fee
A22: NOTES
A23: Tier 1: Early clients, proving model
A24: Tier 2: Growing reputation, more complex projects
A25: Tier 3: Enterprise clients + own GPU infrastructure (0.5% vs 5% API cost)

Sheet Cash Flow
B1: M1 | C1: M2 | D1: M3 | E1: M4 | F1: M5 | G1: M6 | H1: M7 | I1: M8 | J1: M9 | K1: M10 | L1: M11 | M1: M12 | N1: TOTAL
A2: CASH FLOW
A3: Opening Balance | B3: 0 | C3: =B17 -> 32025 | D3: =C17 -> 28050 | E3: =D17 -> 26200 | F3: =E17 -> 23850 | G3: =F17 -> 23625 | H3: =G17 -> 28425 | I3: =H17 -> 134687.5 | J3: =I17 -> 140950 | ... M3: =L17 -> 172800 | O3: =M17 -> 187160 | P3: =O17 -> 206480 | Q3: =P17 -> 229827.5 | R3: =Q17 -> 257202.5 | S3: =R17 -> 287755 | T3: =S17 -> 322335 | U3: =T17 -> 360942.5 | V3: =U17 -> 403577.5 | W3: =V17 -> 449390 | ... Z3: =Y17 -> 610992.5
A4: CASH IN
A5: Investment Received | B5: 40000 | C5: 0 | D5: 0 | E5: 0 | F5: 0 | G5: 0 | H5: 200000 | I5: 0 | J5: 0 | K5: 0 | L5: 0 | M5: 0 | N5: =SUM(B5:M5) -> 240000 | O5: 0 | P5: 0 | Q5: 0 | R5: 0 | S5: 0 | T5: 0 | U5: 0 | V5: 0 | W5: 0 | X5: 0 | Y5: 0 | Z5: 0
A6: Revenue | B6: ='Monthly P&L'!B13 -> 2500 | C6: ='Monthly P&L'!C13 -> 2500 | D6: ='Monthly P&L'!D13 -> 5000 | E6: ='Monthly P&L'!E13 -> 5000 | F6: ='Monthly P&L'!F13 -> 7500 | G6: ='Monthly P&L'!G13 -> 14000 | H6: ='Monthly P&L'!H13 -> 17500 | I6: ='Monthly P&L'!I13 -> 17500 | ... M6: ='Monthly P&L'!M13 -> 28000 | O6: ='Monthly P&L'!O13 -> 36000 | P6: ='Monthly P&L'!P13 -> 40500 | Q6: ='Monthly P&L'!Q13 -> 45000 | R6: ='Monthly P&L'!R13 -> 49500 | S6: ='Monthly P&L'!S13 -> 54000 | T6: ='Monthly P&L'!T13 -> 58500 | U6: ='Monthly P&L'!U13 -> 63000 | V6: ='Monthly P&L'!V13 -> 67500 | ... Z6: ='Monthly P&L'!Z13 -> 90000
A7: Total Cash In | B7: =B5+B6 -> 42500 | C7: =C5+C6 -> 2500 | D7: =D5+D6 -> 5000 | E7: =E5+E6 -> 5000 | F7: =F5+F6 -> 7500 | G7: =G5+G6 -> 14000 | H7: =H5+H6 -> 217500 | I7: =I5+I6 -> 17500 | ... M7: =M5+M6 -> 28000 | O7: =O5+O6 -> 36000 | P7: =P5+P6 -> 40500 | Q7: =Q5+Q6 -> 45000 | R7: =R5+R6 -> 49500 | S7: =S5+S6 -> 54000 | T7: =T5+T6 -> 58500 | U7: =U5+U6 -> 63000 | V7: =V5+V6 -> 67500 | ... Z7: =Z5+Z6 -> 90000
A9: CASH OUT
A10: COGS | B10: ='Monthly P&L'!B18 -> 975 | C10: ='Monthly P&L'!C18 -> 975 | D10: ='Monthly P&L'!D18 -> 1350 | E10: ='Monthly P&L'!E18 -> 1350 | F10: ='Monthly P&L'!F18 -> 1725 | G10: ='Monthly P&L'!G18 -> 2700 | H10: ='Monthly P&L'!H18 -> 2637.5 | I10: ='Monthly P&L'!I18 -> 2637.5 | ... M10: ='Monthly P&L'!M18 -> 3740 | O10: ='Monthly P&L'!O18 -> 4580 | P10: ='Monthly P&L'!P18 -> 5052.5 | Q10: ='Monthly P&L'!Q18 -> 5525 | R10: ='Monthly P&L'!R18 -> 5997.5 | S10: ='Monthly P&L'!S18 -> 6470 | T10: ='Monthly P&L'!T18 -> 6942.5 | U10: ='Monthly P&L'!U18 -> 7415 | V10: ='Monthly P&L'!V18 -> 7887.5 | ... Z10: ='Monthly P&L'!Z18 -> 10250
A11: Operating Expenses (Cash) | B11: ='Monthly P&L'!B28-'Monthly P&L'!B27 -> 5500 | C11: ='Monthly P&L'!C28-'Monthly P&L'!C27 -> 5500 | D11: ='Monthly P&L'!D28-'Monthly P&L'!D27 -> 5500 | E11: ='Monthly P&L'!E28-'Monthly P&L'!E27 -> 6000 | F11: ='Monthly P&L'!F28-'Monthly P&L'!F27 -> 6000 | G11: ='Monthly P&L'!G28-'Monthly P&L'!G27 -> 6500 | H11: ='Monthly P&L'!H28-'Monthly P&L'!H27 -> 8600 | I11: ='Monthly P&L'!I28-'Monthly P&L'!I27 -> 8600 | ... M11: ='Monthly P&L'!M28-'Monthly P&L'!M27 -> 9900 | N11: =SUM(B11:M11) -> 90500 | O11: ='Monthly P&L'!O28-'Monthly P&L'!O27 -> 12100 | P11: ='Monthly P&L'!P28-'Monthly P&L'!P27 -> 12100 | Q11: ='Monthly P&L'!Q28-'Monthly P&L'!Q27 -> 12100 | R11: ='Monthly P&L'!R28-'Monthly P&L'!R27 -> 12950 | S11: ='Monthly P&L'!S28-'Monthly P&L'!S27 -> 12950 | T11: ='Monthly P&L'!T28-'Monthly P&L'!T27 -> 12950 | U11: ='Monthly P&L'!U28-'Monthly P&L'!U27 -> 12950 | V11: ='Monthly P&L'!V28-'Monthly P&L'!V27 -> 13800 | ... Z11: ='Monthly P&L'!Z28-'Monthly P&L'!Z27 -> 13800
A12: Taxes | B12: ='Monthly P&L'!B37 -> 0 | C12: ='Monthly P&L'!C37 -> 0 | D12: ='Monthly P&L'!D37 -> 0 | E12: ='Monthly P&L'!E37 -> 0 | F12: ='Monthly P&L'!F37 -> 0 | G12: ='Monthly P&L'!G37 -> 0 | H12: ='Monthly P&L'!H37 -> 0 | I12: ='Monthly P&L'!I37 -> 0 | ... M12: ='Monthly P&L'!M37 -> 0 | O12: 0 | P12: 0 | Q12: 0 | R12: 0 | S12: 0 | T12: 0 | U12: 0 | V12: 0 | W12: 0 | X12: 0 | Y12: 0 | Z12: 0
A13: CapEx (Equipment) | B13: 4000 | C13: 0 | D13: 0 | E13: 0 | F13: 0 | G13: 0 | H13: 100000 | I13: 0 | J13: 0 | K13: 0 | L13: 0 | M13: 0 | N13: =SUM(B13:M13) -> 104000 | O13: 0 | P13: 0 | Q13: 0 | R13: 0 | S13: 0 | T13: 0 | U13: 0 | V13: 0 | W13: 0 | X13: 0 | Y13: 0 | Z13: 0
A14: Total Cash Out | B14: =B10+B11+B12+B13 -> 10475 | C14: =C10+C11+C12+C13 -> 6475 | D14: =D10+D11+D12+D13 -> 6850 | E14: =E10+E11+E12+E13 -> 7350 | F14: =F10+F11+F12+F13 -> 7725 | G14: =G10+G11+G12+G13 -> 9200 | H14: =H10+H11+H12+H13 -> 111237.5 | I14: =I10+I11+I12+I13 -> 11237.5 | ... M14: =M10+M11+M12+M13 -> 13640 | N14: =SUM(B14:M14) -> 222340 | O14: =O10+O11+O12+O13 -> 16680 | P14: =P10+P11+P12+P13 -> 17152.5 | Q14: =Q10+Q11+Q12+Q13 -> 17625 | R14: =R10+R11+R12+R13 -> 18947.5 | S14: =S10+S11+S12+S13 -> 19420 | T14: =T10+T11+T12+T13 -> 19892.5 | U14: =U10+U11+U12+U13 -> 20365 | V14: =V10+V11+V12+V13 -> 21687.5 | ... Z14: =Z10+Z11+Z12+Z13 -> 24050
A16: Net Cash Flow | B16: =B7-B14 -> 32025 | C16: =C7-C14 -> -3975 | D16: =D7-D14 -> -1850 | E16: =E7-E14 -> -2350 | F16: =F7-F14 -> -225 | G16: =G7-G14 -> 4800 | H16: =H7-H14 -> 106262.5 | I16: =I7-I14 -> 6262.5 | ... M16: =M7-M14 -> 14360 | N16: =SUM(B16:M16) -> 187160 | O16: =O7-O14 -> 19320 | P16: =P7-P14 -> 23347.5 | Q16: =Q7-Q14 -> 27375 | R16: =R7-R14 -> 30552.5 | S16: =S7-S14 -> 34580 | T16: =T7-T14 -> 38607.5 | U16: =U7-U14 -> 42635 | V16: =V7-V14 -> 45812.5 | ... Z16: =Z7-Z14 -> 65950
A17: Closing Balance | B17: =B3+B16 -> 32025 | C17: =C3+C16 -> 28050 | D17: =D3+D16 -> 26200 | E17: =E3+E16 -> 23850 | F17: =F3+F16 -> 23625 | G17: =G3+G16 -> 28425 | H17: =H3+H16 -> 134687.5 | I17: =I3+I16 -> 140950 | ... M17: =M3+M16 -> 187160 | O17: =O3+O16 -> 206480 | P17: =P3+P16 -> 229827.5 | Q17: =Q3+Q16 -> 257202.5 | R17: =R3+R16 -> 287755 | S17: =S3+S16 -> 322335 | T17: =T3+T16 -> 360942.5 | U17: =U3+U16 -> 403577.5 | V17: =V3+V16 -> 449390 | ... Z17: =Z3+Z16 -> 676942.5
A18: Runway (months) | B18: =IF(B16>=0,"∞",B17/(-B16)) -> ∞ | C18: =IF(C16>=0,"∞",C17/(-C16)) -> 7.0566038 | D18: =IF(D16>=0,"∞",D17/(-D16)) -> 14.162162 | E18: =IF(E16>=0,"∞",E17/(-E16)) -> 10.148936 | F18: =IF(F16>=0,"∞",F17/(-F16)) -> 105 | G18: =IF(G16>=0,"∞",G17/(-G16)) -> ∞ | H18: =IF(H16>=0,"∞",H17/(-H16)) -> ∞ | I18: =IF(I16>=0,"∞",I17/(-I16)) -> ∞ | ... M18: =IF(M16>=0,"∞",M17/(-M16)) -> ∞
A19: Break-Even? | B19: =IF(B16>=0,"YES","NO") -> YES | C19: =IF(C16>=0,"YES","NO") -> NO | D19: =IF(D16>=0,"YES","NO") -> NO | E19: =IF(E16>=0,"YES","NO") -> NO | F19: =IF(F16>=0,"YES","NO") -> NO | G19: =IF(G16>=0,"YES","NO") -> YES | H19: =IF(H16>=0,"YES","NO") -> YES | I19: =IF(I16>=0,"YES","NO") -> YES | ... M19: =IF(M16>=0,"YES","NO") -> YES

Sheet Balance Sheet
A1: BALANCE SHEET
A2: As of Month End | B2: M1 | C2: M2 | D2: M3 | E2: M4 | F2: M5 | G2: M6 | H2: M7 | I2: M8 | J2: M9 | K2: M10 | L2: M11 | M2: M12 | O2: M13 | P2: M14 | Q2: M15 | R2: M16 | S2: M17 | T2: M18 | U2: M19 | V2: M20 | W2: M21 | X2: M22 | Y2: M23 | Z2: M24
A4: ASSETS
A5: Cash | B5: ='Cash Flow'!B17 -> 32025 | C5: ='Cash Flow'!C17 -> 28050 | D5: ='Cash Flow'!D17 -> 26200 | E5: ='Cash Flow'!E17 -> 23850 | F5: ='Cash Flow'!F17 -> 23625 | G5: ='Cash Flow'!G17 -> 28425 | H5: ='Cash Flow'!H17 -> 134687.5 | I5: ='Cash Flow'!I17 -> 140950 | ... M5: ='Cash Flow'!M17 -> 187160 | O5: ='Cash Flow'!O17 -> 206480 | P5: ='Cash Flow'!P17 -> 229827.5 | Q5: ='Cash Flow'!Q17 -> 257202.5 | R5: ='Cash Flow'!R17 -> 287755 | S5: ='Cash Flow'!S17 -> 322335 | T5: ='Cash Flow'!T17 -> 360942.5 | U5: ='Cash Flow'!U17 -> 403577.5 | V5: ='Cash Flow'!V17 -> 449390 | ... Z5: ='Cash Flow'!Z17 -> 676942.5
A6: Equipment (Gross) | B6: 4000 | C6: 4000 | D6: 4000 | E6: 4000 | F6: 4000 | G6: 4000 | H6: 104000 | I6: 104000 | J6: 104000 | K6: 104000 | L6: 104000 | M6: 104000 | O6: 104000 | P6: 104000 | Q6: 104000 | R6: 104000 | S6: 104000 | T6: 104000 | U6: 104000 | V6: 104000 | W6: 104000 | X6: 104000 | Y6: 104000 | Z6: 104000
A7: Accumulated Depreciation | B7: -67 | C7: =B7-67 -> -134 | D7: =C7-67 -> -201 | E7: =D7-67 -> -268 | F7: =E7-67 -> -335 | G7: =F7-67 -> -402 | H7: =G7-1733 -> -2135 | I7: =H7-1733 -> -3868 | J7: =I7-1733 -> -5601 | K7: =J7-1733 -> -7334 | L7: =K7-1733 -> -9067 | M7: =L7-1733 -> -10800 | O7: =M7-1733 -> -12533 | P7: =O7-1733 -> -14266 | Q7: =P7-1733 -> -15999 | R7: =Q7-1733 -> -17732 | S7: =R7-1733 -> -19465 | T7: =S7-1733 -> -21198 | U7: =T7-1733 -> -22931 | V7: =U7-1733 -> -24664 | W7: =V7-1733 -> -26397 | ... Z7: =Y7-1733 -> -31596
A8: Net Fixed Assets | B8: =B6+B7 -> 3933 | C8: =C6+C7 -> 3866 | D8: =D6+D7 -> 3799 | E8: =E6+E7 -> 3732 | F8: =F6+F7 -> 3665 | G8: =G6+G7 -> 3598 | H8: =H6+H7 -> 101865 | I8: =I6+I7 -> 100132 | ... M8: =M6+M7 -> 93200 | O8: =O6+O7 -> 91467 | P8: =P6+P7 -> 89734 | Q8: =Q6+Q7 -> 88001 | R8: =R6+R7 -> 86268 | S8: =S6+S7 -> 84535 | T8: =T6+T7 -> 82802 | U8: =U6+U7 -> 81069 | V8: =V6+V7 -> 79336 | ... Z8: =Z6+Z7 -> 72404
A10: TOTAL ASSETS | B10: =B5+B8 -> 35958 | C10: =C5+C8 -> 31916 | D10: =D5+D8 -> 29999 | E10: =E5+E8 -> 27582 | F10: =F5+F8 -> 27290 | G10: =G5+G8 -> 32023 | H10: =H5+H8 -> 236552.5 | I10: =I5+I8 -> 241082 | ... M10: =M5+M8 -> 280360 | O10: =O5+O8 -> 297947 | P10: =P5+P8 -> 319561.5 | Q10: =Q5+Q8 -> 345203.5 | R10: =R5+R8 -> 374023 | S10: =S5+S8 -> 406870 | T10: =T5+T8 -> 443744.5 | U10: =U5+U8 -> 484646.5 | V10: =V5+V8 -> 528726 | ... Z10: =Z5+Z8 -> 749346.5
A12: LIABILITIES & EQUITY
A13: Liabilities | B13: 0 | C13: 0 | D13: 0 | E13: 0 | F13: 0 | G13: 0 | H13: 0 | I13: 0 | J13: 0 | K13: 0 | L13: 0 | M13: 0 | O13: 0 | P13: 0 | Q13: 0 | R13: 0 | S13: 0 | T13: 0 | U13: 0 | V13: 0 | W13: 0 | X13: 0 | Y13: 0 | Z13: 0
A15: Contributed Capital | B15: 40000 | C15: 40000 | D15: 40000 | E15: 40000 | F15: 40000 | G15: 40000 | H15: 240000 | I15: 240000 | J15: 240000 | K15: 240000 | L15: 240000 | M15: 240000 | O15: 240000 | P15: 240000 | Q15: 240000 | R15: 240000 | S15: 240000 | T15: 240000 | U15: 240000 | V15: 240000 | W15: 240000 | X15: 240000 | Y15: 240000 | Z15: 240000
A16: Retained Earnings | B16: ='Monthly P&L'!B39 -> -4042 | C16: =B16+'Monthly P&L'!C39 -> -8084 | D16: =C16+'Monthly P&L'!D39 -> -10001 | E16: =D16+'Monthly P&L'!E39 -> -12418 | F16: =E16+'Monthly P&L'!F39 -> -12710 | G16: =F16+'Monthly P&L'!G39 -> -7977 | H16: =G16+'Monthly P&L'!H39 -> -3447.5 | I16: =H16+'Monthly P&L'!I39 -> 1082 | J16: =I16+'Monthly P&L'!J39 -> 8094 | ... M16: =L16+'Monthly P&L'!M39 -> 40360 | O16: =M16+'Monthly P&L'!O39 -> 57947 | P16: =O16+'Monthly P&L'!P39 -> 79561.5 | Q16: =P16+'Monthly P&L'!Q39 -> 105203.5 | R16: =Q16+'Monthly P&L'!R39 -> 134023 | S16: =R16+'Monthly P&L'!S39 -> 166870 | T16: =S16+'Monthly P&L'!T39 -> 203744.5 | U16: =T16+'Monthly P&L'!U39 -> 244646.5 | V16: =U16+'Monthly P&L'!V39 -> 288726 | W16: =V16+'Monthly P&L'!W39 -> 336833 | ... Z16: =Y16+'Monthly P&L'!Z39 -> 509346.5
A17: Total Equity | B17: =B15+B16 -> 35958 | C17: =C15+C16 -> 31916 | D17: =D15+D16 -> 29999 | E17: =E15+E16 -> 27582 | F17: =F15+F16 -> 27290 | G17: =G15+G16 -> 32023 | H17: =H15+H16 -> 236552.5 | I17: =I15+I16 -> 241082 | ... M17: =M15+M16 -> 280360 | O17: =O15+O16 -> 297947 | P17: =P15+P16 -> 319561.5 | Q17: =Q15+Q16 -> 345203.5 | R17: =R15+R16 -> 374023 | S17: =S15+S16 -> 406870 | T17: =T15+T16 -> 443744.5 | U17: =U15+U16 -> 484646.5 | V17: =V15+V16 -> 528726 | ... Z17: =Z15+Z16 -> 749346.5
A19: TOTAL LIABILITIES + EQUITY | B19: =B13+B17 -> 35958 | C19: =C13+C17 -> 31916 | D19: =D13+D17 -> 29999 | E19: =E13+E17 -> 27582 | F19: =F13+F17 -> 27290 | G19: =G13+G17 -> 32023 | H19: =H13+H17 -> 236552.5 | I19: =I13+I17 -> 241082 | ... M19: =M13+M17 -> 280360 | O19: =O13+O17 -> 297947 | P19: =P13+P17 -> 319561.5 | Q19: =Q13+Q17 -> 345203.5 | R19: =R13+R17 -> 374023 | S19: =S13+S17 -> 406870 | T19: =T13+T17 -> 443744.5 | U19: =U13+U17 -> 484646.5 | V19: =V13+V17 -> 528726 | ... Z19: =Z13+Z17 -> 749346.5
A21: Balance Check (should be 0) | B21: =B10-B19 -> 0 | C21: =C10-C19 -> 0 | D21: =D10-D19 -> 0 | E21: =E10-E19 -> 0 | F21: =F10-F19 -> 0 | G21: =G10-G19 -> 0 | H21: =H10-H19 -> 0 | I21: =I10-I19 -> 0 | ... M21: =M10-M19 -> 0 | O21: =O10-O19 -> 0 | P21: =P10-P19 -> 0 | Q21: =Q10-Q19 -> 0 | R21: =R10-R19 -> 0 | S21: =S10-S19 -> 0 | T21: =T10-T19 -> 0 | U21: =U10-U19 -> 0 | V21: =V10-V19 -> 0 | ... Z21: =Z10-Z19 -> 0

Sheet Use of Funds
A1: USE OF FUNDS
A3: STAGE 1: PRE-SEED | B3: $40,000 | C3: M1-6
A5: Tech Team (6 months) | B5: 6000 | C5: 0.15
A6: Founder Salary (6 months) | B6: 18000 | C6: 0.45
A7: Marketing (6 months) | B7: 9000 | C7: 0.225
A8: Infrastructure | B8: 7000 | C8: 0.175
A9: Total | B9: =SUM(B5:B8) -> 40000 | C9: 1
A12: STAGE 2: SEED | B12: $200,000 | C12: M7-18
A14: Infrastructure (4×A100) | B14: 100000 | C14: 0.5
A15: Team Expansion | B15: 50000 | C15: 0.25
A16: Go-to-Market | B16: 30000 | C16: 0.15
A17: Product & R&D | B17: 15000 | C17: 0.075
A18: Contingency | B18: 5000 | C18: 0.025
A19: Total | B19: =SUM(B14:B18) -> 200000 | C19: 1
